emb3d/__init__.py
emb3d/client.py
emb3d/compute/__init__.py
emb3d/compute/common.py
emb3d/compute/local.py
emb3d/compute/remote.py
emb3d/compute/test_common.py
emb3d/compute/test_local.py
emb3d/compute/visualize.py
emb3d/config.py
emb3d/main.py
emb3d/reader.py
emb3d/test_utils.py
emb3d/textui.py
emb3d/types.py
emb3d-0.1.106.dist-info/METADATA
emb3d-0.1.106.dist-info/WHEEL
emb3d-0.1.106.dist-info/entry_points.txt
emb3d-0.1.106.dist-info/RECORD
