Metadata-Version: 2.1
Name: emb3d
Version: 0.1.106
Summary: emb3d.co command line inteface to work with embeddings.
Author: Akhil Ravidas
Author-email: ar@mod0.ai
Requires-Python: >=3.9,<3.13
Classifier: Programming Language :: Python :: 3
Classifier: Programming Language :: Python :: 3.9
Classifier: Programming Language :: Python :: 3.10
Classifier: Programming Language :: Python :: 3.11
Requires-Dist: aiolimiter (>=1.1.0,<2.0.0)
Requires-Dist: altair (>=5.1.2,<6.0.0)
Requires-Dist: cohere (>=4.27,<5.0)
Requires-Dist: hdbscan (>=0.8.33,<0.9.0)
Requires-Dist: httpx (>=0.25.0,<0.26.0)
Requires-Dist: numpy (>=1.25,<2.0)
Requires-Dist: openai (>=0.28.1,<0.29.0)
Requires-Dist: pandas (>=2.1.1,<3.0.0)
Requires-Dist: pyyaml (>=6.0.1,<7.0.0)
Requires-Dist: sentence-transformers (>=2.2.2,<3.0.0)
Requires-Dist: tiktoken (>=0.5.1,<0.6.0)
Requires-Dist: tokenizers (>=0.14.0,<0.15.0)
Requires-Dist: typer[all] (>=0.9.0,<0.10.0)
